qjobs/__init__.py
qjobs/__main__.py
qjobs/commands.py
qjobs/config.py
qjobs/constants.py
qjobs/job.py
qjobs/misc.py
qjobs-0.2.0.dist-info/LICENSE.rst
qjobs-0.2.0.dist-info/METADATA
qjobs-0.2.0.dist-info/WHEEL
qjobs-0.2.0.dist-info/entry_points.txt
qjobs-0.2.0.dist-info/top_level.txt
qjobs-0.2.0.dist-info/RECORD
