Metadata-Version: 2.1
Name: qjobs
Version: 0.2.0
Summary: Get a clean and flexible output from qstat
Home-page: https://github.com/amorison/qjobs
Author: Adrien Morison
Author-email: adrien.morison@gmail.com
License: MIT
Platform: UNKNOWN
Classifier: Development Status :: 4 - Beta
Classifier: Intended Audience :: Information Technology
Classifier: Intended Audience :: Science/Research
Classifier: License :: OSI Approved :: MIT License
Classifier: Programming Language :: Python :: 3 :: Only
Classifier: Programming Language :: Python :: 3.6
Classifier: Programming Language :: Python :: 3.7
Classifier: Programming Language :: Python :: 3.8
Classifier: Programming Language :: Python :: 3.9
Requires-Python: >=3.6
Requires-Dist: setuptools-scm
Requires-Dist: loam (>=0.3.1)
